CHANGELOG.md
pushbroom.conf
pushbroom/__init__.py
pushbroom/console.py
pushbroom/sweep.py
pushbroom-1.0.0.dist-info/entry_points.txt
pushbroom-1.0.0.dist-info/LICENSE
pushbroom-1.0.0.dist-info/WHEEL
pushbroom-1.0.0.dist-info/METADATA
pushbroom-1.0.0.dist-info/RECORD
