Metadata-Version: 2.1
Name: pushbroom
Version: 1.0.0
Summary: Clean up your filesystem
Home-page: https://github.com/gpanders/pushbroom
License: MIT
Author: Gregory Anders
Author-email: greg@gpanders.com
Requires-Python: >=3.6,<4.0
Classifier: License :: OSI Approved :: MIT License
Classifier: Programming Language :: Python :: 3
Classifier: Programming Language :: Python :: 3.6
Classifier: Programming Language :: Python :: 3.7
Classifier: Programming Language :: Python :: 3.8
Classifier: Programming Language :: Python :: 3.9
Project-URL: Repository, https://github.com/gpanders/pushbroom
